LICENSE
README.md
eox_notices/__init__.py
eox_notices/admin.py
eox_notices/api/__init__.py
eox_notices/api/serializers.py
eox_notices/api/urls.py
eox_notices/api/views.py
eox_notices/filters.py
eox_notices/forms.py
eox_notices/migrations/0001_initial.py
eox_notices/migrations/__init__.py
eox_notices/models.py
eox_notices/navigation.py
eox_notices/signals.py
eox_notices/tables.py
eox_notices/template_content.py
eox_notices/templates/eox_notices/eox_notice_delete.html
eox_notices/templates/eox_notices/eoxnotice.html
eox_notices/templates/eox_notices/inc/general_notice.html
eox_notices/tests/__init__.py
eox_notices/tests/test_api.py
eox_notices/tests/test_filters.py
eox_notices/tests/test_forms.py
eox_notices/tests/test_model.py
eox_notices/tests/test_views.py
eox_notices/urls.py
eox_notices/views.py
nautobot_eox_notices-0.2.0.dist-info/LICENSE
nautobot_eox_notices-0.2.0.dist-info/WHEEL
nautobot_eox_notices-0.2.0.dist-info/METADATA
nautobot_eox_notices-0.2.0.dist-info/RECORD
