Metadata-Version: 2.1
Name: nautobot-eox-notices
Version: 0.2.0
Summary: Tracks EoX Notices for Nautobot objects.
Home-page: https://github.com/fragmentedpacket/nautobot-eox-notices
License: Apache-2.0
Keywords: nautobot,nautobot-plugin
Author: Mikhail Yohman
Author-email: mikhail.yohman@gmail.com
Requires-Python: >=3.6.2,<4.0.0
Classifier: License :: OSI Approved :: Apache Software License
Classifier: Programming Language :: Python :: 3
Classifier: Programming Language :: Python :: 3.7
Classifier: Programming Language :: Python :: 3.8
Classifier: Programming Language :: Python :: 3.9
Provides-Extra: nautobot
Requires-Dist: nautobot; extra == "nautobot"
Project-URL: Repository, https://github.com/fragmentedpacket/nautobot-eox-notices
